drone_plugin_exec/__init__.py
drone_plugin_exec/config.py
drone_plugin_exec/context.py
drone_plugin_exec/keys.py
drone_plugin_exec/log.py
drone_plugin_exec/packet.py
drone_plugin_exec/script.py
drone_plugin_exec/plugin/__init__.py
drone_plugin_exec/plugin/__main__.py
drone_plugin_exec/plugin/config.py
drone_plugin_exec/plugin/sender.py
drone_plugin_exec/target/__init__.py
drone_plugin_exec/target/__main__.py
drone_plugin_exec/target/config.py
drone_plugin_exec/target/daemon.py
drone_plugin_exec/target/environment.py
drone_plugin_exec-0.1.1.dist-info/LICENSE
drone_plugin_exec-0.1.1.dist-info/METADATA
drone_plugin_exec-0.1.1.dist-info/WHEEL
drone_plugin_exec-0.1.1.dist-info/entry_points.txt
drone_plugin_exec-0.1.1.dist-info/top_level.txt
drone_plugin_exec-0.1.1.dist-info/RECORD
