Metadata-Version: 2.1
Name: drone-plugin-exec
Version: 0.1.1
Summary: The guts of a drone plugin that runs code on the machines the containers are on.
Home-page: https://github.com/haxwithaxe/drone-plugin-exec/
Author: haxwithaxe
Author-email: spam@haxwithaxe.net
License: GPLv3
Project-URL: Source, https://github.com/haxwithaxe/drone-plugin-exec/
Project-URL: Tracker, https://github.com/haxwithaxe/drone-plugin-exec/issues
Project-URL: Download, https://pypi.org/project/drone-plugin-exec/#files
Platform: any
Classifier: Environment :: Plugins
Classifier: Intended Audience :: Other Audience
Classifier: License :: OSI Approved :: GNU General Public License v3 or later (GPLv3+)
Requires-Python: >=3.9
License-File: LICENSE
Requires-Dist: PyNaCl
Requires-Dist: GitPython
Requires-Dist: typer
Requires-Dist: docker
Requires-Dist: toml ; python_version < "3.11"
Provides-Extra: lint
Requires-Dist: isort ; extra == 'lint'
Requires-Dist: flake8 ; extra == 'lint'
